mfgsolver/__init__.py
mfgsolver/base.py
mfgsolver/ergodic.py
mfgsolver-0.4.4.dist-info/WHEEL
mfgsolver-0.4.4.dist-info/METADATA
mfgsolver-0.4.4.dist-info/RECORD
